{
  "appPageId" : "472aa17a-db19-4171-aa91-516c8bef0edc",
  "componentName" : "siteforce:sldsOneColLayout",
  "dataProviders" : [ ],
  "id" : "64303a8e-a74e-46d6-857a-de2c1eba0f7e",
  "label" : "Action Plan Template Related List",
  "regions" : [ {
    "id" : "893597c8-98c1-41db-88e3-d7d8bb014c23",
    "regionName" : "header",
    "type" : "region"
  }, {
    "components" : [ {
      "componentAttributes" : {
        "customTitle" : "",
        "parentRecordId" : "{!recordId}",
        "relatedListName" : "{!relationshipApiName}",
        "showBreadCrumbs" : true,
        "showCustomTitle" : false,
        "showManualRefreshButton" : true,
        "showRowNumbers" : true
      },
      "componentName" : "forceCommunity:relatedList",
      "id" : "abafff78-595a-47d3-917f-bb3639f682fb",
      "renderPriority" : "NEUTRAL",
      "renditionMap" : { },
      "type" : "component"
    } ],
    "id" : "05cb786a-cbeb-44ec-a830-3950119d0ce8",
    "regionName" : "content",
    "type" : "region"
  }, {
    "id" : "548e66fa-150b-49b6-9798-db33c646e4c8",
    "regionName" : "footer",
    "type" : "region"
  } ],
  "themeLayoutType" : "Inner",
  "type" : "view",
  "viewType" : "relatedlist-0PR"
}